<annotation>
	<folder></folder>
	<filename>11_Meeting_Meeting_11_Meeting_Meeting_11_663_jpg.rf.f332525df0695f756104f94bbce3c1f8.jpg</filename>
	<path>11_Meeting_Meeting_11_Meeting_Meeting_11_663_jpg.rf.f332525df0695f756104f94bbce3c1f8.jpg</path>
	<source>
		<database>roboflow.ai</database>
	</source>
	<size>
		<width>1024</width>
		<height>615</height>
		<depth>3</depth>
	</size>
	<segmented>0</segmented>
	<object>
		<name>face</name>
		<pose>Unspecified</pose>
		<truncated>0</truncated>
		<difficult>0</difficult>
		<occluded>0</occluded>
		<bndbox>
			<xmin>1</xmin>
			<xmax>1</xmax>
			<ymin>1</ymin>
			<ymax>1</ymax>
		</bndbox>
	</object>
	<object>
		<name>face</name>
		<pose>Unspecified</pose>
		<truncated>0</truncated>
		<difficult>0</difficult>
		<occluded>0</occluded>
		<bndbox>
			<xmin>132</xmin>
			<xmax>143</xmax>
			<ymin>482</ymin>
			<ymax>499</ymax>
		</bndbox>
	</object>
	<object>
		<name>face</name>
		<pose>Unspecified</pose>
		<truncated>0</truncated>
		<difficult>0</difficult>
		<occluded>0</occluded>
		<bndbox>
			<xmin>101</xmin>
			<xmax>115</xmax>
			<ymin>479</ymin>
			<ymax>496</ymax>
		</bndbox>
	</object>
	<object>
		<name>face</name>
		<pose>Unspecified</pose>
		<truncated>0</truncated>
		<difficult>0</difficult>
		<occluded>0</occluded>
		<bndbox>
			<xmin>80</xmin>
			<xmax>90</xmax>
			<ymin>481</ymin>
			<ymax>495</ymax>
		</bndbox>
	</object>
	<object>
		<name>face</name>
		<pose>Unspecified</pose>
		<truncated>0</truncated>
		<difficult>0</difficult>
		<occluded>0</occluded>
		<bndbox>
			<xmin>82</xmin>
			<xmax>94</xmax>
			<ymin>511</ymin>
			<ymax>524</ymax>
		</bndbox>
	</object>
	<object>
		<name>face</name>
		<pose>Unspecified</pose>
		<truncated>0</truncated>
		<difficult>0</difficult>
		<occluded>0</occluded>
		<bndbox>
			<xmin>58</xmin>
			<xmax>73</xmax>
			<ymin>511</ymin>
			<ymax>528</ymax>
		</bndbox>
	</object>
	<object>
		<name>face</name>
		<pose>Unspecified</pose>
		<truncated>0</truncated>
		<difficult>0</difficult>
		<occluded>0</occluded>
		<bndbox>
			<xmin>38</xmin>
			<xmax>51</xmax>
			<ymin>507</ymin>
			<ymax>525</ymax>
		</bndbox>
	</object>
	<object>
		<name>face</name>
		<pose>Unspecified</pose>
		<truncated>0</truncated>
		<difficult>0</difficult>
		<occluded>0</occluded>
		<bndbox>
			<xmin>33</xmin>
			<xmax>43</xmax>
			<ymin>528</ymin>
			<ymax>544</ymax>
		</bndbox>
	</object>
	<object>
		<name>face</name>
		<pose>Unspecified</pose>
		<truncated>0</truncated>
		<difficult>0</difficult>
		<occluded>0</occluded>
		<bndbox>
			<xmin>3</xmin>
			<xmax>16</xmax>
			<ymin>536</ymin>
			<ymax>554</ymax>
		</bndbox>
	</object>
	<object>
		<name>face</name>
		<pose>Unspecified</pose>
		<truncated>0</truncated>
		<difficult>0</difficult>
		<occluded>0</occluded>
		<bndbox>
			<xmin>1</xmin>
			<xmax>10</xmax>
			<ymin>501</ymin>
			<ymax>516</ymax>
		</bndbox>
	</object>
	<object>
		<name>face</name>
		<pose>Unspecified</pose>
		<truncated>0</truncated>
		<difficult>0</difficult>
		<occluded>0</occluded>
		<bndbox>
			<xmin>30</xmin>
			<xmax>38</xmax>
			<ymin>480</ymin>
			<ymax>491</ymax>
		</bndbox>
	</object>
	<object>
		<name>face</name>
		<pose>Unspecified</pose>
		<truncated>0</truncated>
		<difficult>0</difficult>
		<occluded>0</occluded>
		<bndbox>
			<xmin>103</xmin>
			<xmax>118</xmax>
			<ymin>515</ymin>
			<ymax>529</ymax>
		</bndbox>
	</object>
	<object>
		<name>face</name>
		<pose>Unspecified</pose>
		<truncated>0</truncated>
		<difficult>0</difficult>
		<occluded>0</occluded>
		<bndbox>
			<xmin>242</xmin>
			<xmax>292</xmax>
			<ymin>216</ymin>
			<ymax>284</ymax>
		</bndbox>
	</object>
	<object>
		<name>face</name>
		<pose>Unspecified</pose>
		<truncated>0</truncated>
		<difficult>0</difficult>
		<occluded>0</occluded>
		<bndbox>
			<xmin>974</xmin>
			<xmax>981</xmax>
			<ymin>274</ymin>
			<ymax>282</ymax>
		</bndbox>
	</object>
	<object>
		<name>face</name>
		<pose>Unspecified</pose>
		<truncated>0</truncated>
		<difficult>0</difficult>
		<occluded>0</occluded>
		<bndbox>
			<xmin>1000</xmin>
			<xmax>1006</xmax>
			<ymin>270</ymin>
			<ymax>278</ymax>
		</bndbox>
	</object>
	<object>
		<name>face</name>
		<pose>Unspecified</pose>
		<truncated>0</truncated>
		<difficult>0</difficult>
		<occluded>0</occluded>
		<bndbox>
			<xmin>1011</xmin>
			<xmax>1018</xmax>
			<ymin>270</ymin>
			<ymax>279</ymax>
		</bndbox>
	</object>
	<object>
		<name>face</name>
		<pose>Unspecified</pose>
		<truncated>0</truncated>
		<difficult>0</difficult>
		<occluded>0</occluded>
		<bndbox>
			<xmin>871</xmin>
			<xmax>875</xmax>
			<ymin>309</ymin>
			<ymax>315</ymax>
		</bndbox>
	</object>
</annotation>
