<annotation>
	<folder></folder>
	<filename>19_Couple_Couple_19_743_jpg.rf.091d29c9d78c0f3bf205ab87ba1defb5.jpg</filename>
	<path>19_Couple_Couple_19_743_jpg.rf.091d29c9d78c0f3bf205ab87ba1defb5.jpg</path>
	<source>
		<database>roboflow.ai</database>
	</source>
	<size>
		<width>1024</width>
		<height>753</height>
		<depth>3</depth>
	</size>
	<segmented>0</segmented>
	<object>
		<name>face</name>
		<pose>Unspecified</pose>
		<truncated>0</truncated>
		<difficult>0</difficult>
		<occluded>0</occluded>
		<bndbox>
			<xmin>1</xmin>
			<xmax>1</xmax>
			<ymin>1</ymin>
			<ymax>1</ymax>
		</bndbox>
	</object>
	<object>
		<name>face</name>
		<pose>Unspecified</pose>
		<truncated>0</truncated>
		<difficult>0</difficult>
		<occluded>0</occluded>
		<bndbox>
			<xmin>859</xmin>
			<xmax>892</xmax>
			<ymin>302</ymin>
			<ymax>343</ymax>
		</bndbox>
	</object>
	<object>
		<name>face</name>
		<pose>Unspecified</pose>
		<truncated>0</truncated>
		<difficult>0</difficult>
		<occluded>0</occluded>
		<bndbox>
			<xmin>802</xmin>
			<xmax>838</xmax>
			<ymin>299</ymin>
			<ymax>341</ymax>
		</bndbox>
	</object>
	<object>
		<name>face</name>
		<pose>Unspecified</pose>
		<truncated>0</truncated>
		<difficult>0</difficult>
		<occluded>0</occluded>
		<bndbox>
			<xmin>734</xmin>
			<xmax>749</xmax>
			<ymin>199</ymin>
			<ymax>223</ymax>
		</bndbox>
	</object>
	<object>
		<name>face</name>
		<pose>Unspecified</pose>
		<truncated>0</truncated>
		<difficult>0</difficult>
		<occluded>0</occluded>
		<bndbox>
			<xmin>760</xmin>
			<xmax>785</xmax>
			<ymin>215</ymin>
			<ymax>240</ymax>
		</bndbox>
	</object>
	<object>
		<name>face</name>
		<pose>Unspecified</pose>
		<truncated>0</truncated>
		<difficult>0</difficult>
		<occluded>0</occluded>
		<bndbox>
			<xmin>758</xmin>
			<xmax>788</xmax>
			<ymin>249</ymin>
			<ymax>284</ymax>
		</bndbox>
	</object>
	<object>
		<name>face</name>
		<pose>Unspecified</pose>
		<truncated>0</truncated>
		<difficult>0</difficult>
		<occluded>0</occluded>
		<bndbox>
			<xmin>697</xmin>
			<xmax>728</xmax>
			<ymin>411</ymin>
			<ymax>447</ymax>
		</bndbox>
	</object>
	<object>
		<name>face</name>
		<pose>Unspecified</pose>
		<truncated>0</truncated>
		<difficult>0</difficult>
		<occluded>0</occluded>
		<bndbox>
			<xmin>670</xmin>
			<xmax>700</xmax>
			<ymin>394</ymin>
			<ymax>427</ymax>
		</bndbox>
	</object>
	<object>
		<name>face</name>
		<pose>Unspecified</pose>
		<truncated>0</truncated>
		<difficult>0</difficult>
		<occluded>0</occluded>
		<bndbox>
			<xmin>597</xmin>
			<xmax>622</xmax>
			<ymin>319</ymin>
			<ymax>346</ymax>
		</bndbox>
	</object>
	<object>
		<name>face</name>
		<pose>Unspecified</pose>
		<truncated>0</truncated>
		<difficult>0</difficult>
		<occluded>0</occluded>
		<bndbox>
			<xmin>638</xmin>
			<xmax>658</xmax>
			<ymin>324</ymin>
			<ymax>352</ymax>
		</bndbox>
	</object>
	<object>
		<name>face</name>
		<pose>Unspecified</pose>
		<truncated>0</truncated>
		<difficult>0</difficult>
		<occluded>0</occluded>
		<bndbox>
			<xmin>523</xmin>
			<xmax>558</xmax>
			<ymin>272</ymin>
			<ymax>319</ymax>
		</bndbox>
	</object>
	<object>
		<name>face</name>
		<pose>Unspecified</pose>
		<truncated>0</truncated>
		<difficult>0</difficult>
		<occluded>0</occluded>
		<bndbox>
			<xmin>450</xmin>
			<xmax>478</xmax>
			<ymin>303</ymin>
			<ymax>343</ymax>
		</bndbox>
	</object>
	<object>
		<name>face</name>
		<pose>Unspecified</pose>
		<truncated>0</truncated>
		<difficult>0</difficult>
		<occluded>0</occluded>
		<bndbox>
			<xmin>321</xmin>
			<xmax>347</xmax>
			<ymin>214</ymin>
			<ymax>248</ymax>
		</bndbox>
	</object>
	<object>
		<name>face</name>
		<pose>Unspecified</pose>
		<truncated>0</truncated>
		<difficult>0</difficult>
		<occluded>0</occluded>
		<bndbox>
			<xmin>404</xmin>
			<xmax>437</xmax>
			<ymin>305</ymin>
			<ymax>343</ymax>
		</bndbox>
	</object>
	<object>
		<name>face</name>
		<pose>Unspecified</pose>
		<truncated>0</truncated>
		<difficult>0</difficult>
		<occluded>0</occluded>
		<bndbox>
			<xmin>156</xmin>
			<xmax>189</xmax>
			<ymin>310</ymin>
			<ymax>347</ymax>
		</bndbox>
	</object>
	<object>
		<name>face</name>
		<pose>Unspecified</pose>
		<truncated>0</truncated>
		<difficult>0</difficult>
		<occluded>0</occluded>
		<bndbox>
			<xmin>127</xmin>
			<xmax>158</xmax>
			<ymin>319</ymin>
			<ymax>356</ymax>
		</bndbox>
	</object>
	<object>
		<name>face</name>
		<pose>Unspecified</pose>
		<truncated>0</truncated>
		<difficult>0</difficult>
		<occluded>0</occluded>
		<bndbox>
			<xmin>184</xmin>
			<xmax>204</xmax>
			<ymin>474</ymin>
			<ymax>508</ymax>
		</bndbox>
	</object>
	<object>
		<name>face</name>
		<pose>Unspecified</pose>
		<truncated>0</truncated>
		<difficult>0</difficult>
		<occluded>0</occluded>
		<bndbox>
			<xmin>281</xmin>
			<xmax>303</xmax>
			<ymin>415</ymin>
			<ymax>454</ymax>
		</bndbox>
	</object>
	<object>
		<name>face</name>
		<pose>Unspecified</pose>
		<truncated>0</truncated>
		<difficult>0</difficult>
		<occluded>0</occluded>
		<bndbox>
			<xmin>699</xmin>
			<xmax>709</xmax>
			<ymin>118</ymin>
			<ymax>129</ymax>
		</bndbox>
	</object>
</annotation>
