<annotation>
	<folder></folder>
	<filename>6_Funeral_Funeral_6_676_jpg.rf.7c3d2a83ceb5fc09ee0346f4bfabd84b.jpg</filename>
	<path>6_Funeral_Funeral_6_676_jpg.rf.7c3d2a83ceb5fc09ee0346f4bfabd84b.jpg</path>
	<source>
		<database>roboflow.ai</database>
	</source>
	<size>
		<width>1024</width>
		<height>582</height>
		<depth>3</depth>
	</size>
	<segmented>0</segmented>
	<object>
		<name>face</name>
		<pose>Unspecified</pose>
		<truncated>0</truncated>
		<difficult>0</difficult>
		<occluded>0</occluded>
		<bndbox>
			<xmin>1</xmin>
			<xmax>1</xmax>
			<ymin>1</ymin>
			<ymax>1</ymax>
		</bndbox>
	</object>
	<object>
		<name>face</name>
		<pose>Unspecified</pose>
		<truncated>0</truncated>
		<difficult>0</difficult>
		<occluded>0</occluded>
		<bndbox>
			<xmin>617</xmin>
			<xmax>668</xmax>
			<ymin>259</ymin>
			<ymax>335</ymax>
		</bndbox>
	</object>
	<object>
		<name>face</name>
		<pose>Unspecified</pose>
		<truncated>0</truncated>
		<difficult>0</difficult>
		<occluded>0</occluded>
		<bndbox>
			<xmin>498</xmin>
			<xmax>534</xmax>
			<ymin>251</ymin>
			<ymax>300</ymax>
		</bndbox>
	</object>
	<object>
		<name>face</name>
		<pose>Unspecified</pose>
		<truncated>0</truncated>
		<difficult>0</difficult>
		<occluded>0</occluded>
		<bndbox>
			<xmin>559</xmin>
			<xmax>612</xmax>
			<ymin>145</ymin>
			<ymax>214</ymax>
		</bndbox>
	</object>
	<object>
		<name>face</name>
		<pose>Unspecified</pose>
		<truncated>0</truncated>
		<difficult>0</difficult>
		<occluded>0</occluded>
		<bndbox>
			<xmin>319</xmin>
			<xmax>361</xmax>
			<ymin>274</ymin>
			<ymax>303</ymax>
		</bndbox>
	</object>
	<object>
		<name>face</name>
		<pose>Unspecified</pose>
		<truncated>0</truncated>
		<difficult>0</difficult>
		<occluded>0</occluded>
		<bndbox>
			<xmin>733</xmin>
			<xmax>761</xmax>
			<ymin>38</ymin>
			<ymax>78</ymax>
		</bndbox>
	</object>
	<object>
		<name>face</name>
		<pose>Unspecified</pose>
		<truncated>0</truncated>
		<difficult>0</difficult>
		<occluded>0</occluded>
		<bndbox>
			<xmin>854</xmin>
			<xmax>888</xmax>
			<ymin>46</ymin>
			<ymax>88</ymax>
		</bndbox>
	</object>
	<object>
		<name>face</name>
		<pose>Unspecified</pose>
		<truncated>0</truncated>
		<difficult>0</difficult>
		<occluded>0</occluded>
		<bndbox>
			<xmin>907</xmin>
			<xmax>954</xmax>
			<ymin>238</ymin>
			<ymax>297</ymax>
		</bndbox>
	</object>
	<object>
		<name>face</name>
		<pose>Unspecified</pose>
		<truncated>0</truncated>
		<difficult>0</difficult>
		<occluded>0</occluded>
		<bndbox>
			<xmin>663</xmin>
			<xmax>705</xmax>
			<ymin>183</ymin>
			<ymax>233</ymax>
		</bndbox>
	</object>
	<object>
		<name>face</name>
		<pose>Unspecified</pose>
		<truncated>0</truncated>
		<difficult>0</difficult>
		<occluded>0</occluded>
		<bndbox>
			<xmin>646</xmin>
			<xmax>678</xmax>
			<ymin>58</ymin>
			<ymax>109</ymax>
		</bndbox>
	</object>
	<object>
		<name>face</name>
		<pose>Unspecified</pose>
		<truncated>0</truncated>
		<difficult>0</difficult>
		<occluded>0</occluded>
		<bndbox>
			<xmin>255</xmin>
			<xmax>312</xmax>
			<ymin>391</ymin>
			<ymax>435</ymax>
		</bndbox>
	</object>
</annotation>
