<annotation>
	<folder></folder>
	<filename>img_503_jpg.rf.6a35705a2fb5e3b28934212dc4fa2ae0.jpg</filename>
	<path>img_503_jpg.rf.6a35705a2fb5e3b28934212dc4fa2ae0.jpg</path>
	<source>
		<database>roboflow.ai</database>
	</source>
	<size>
		<width>416</width>
		<height>416</height>
		<depth>3</depth>
	</size>
	<segmented>0</segmented>
	<object>
		<name>face</name>
		<pose>Unspecified</pose>
		<truncated>0</truncated>
		<difficult>0</difficult>
		<occluded>0</occluded>
		<bndbox>
			<xmin>135</xmin>
			<xmax>261</xmax>
			<ymin>35</ymin>
			<ymax>291</ymax>
		</bndbox>
	</object>
</annotation>
