<annotation>
	<folder></folder>
	<filename>img_126_jpg.rf.266efee862ddcde08ca04c4f7908ef57.jpg</filename>
	<path>img_126_jpg.rf.266efee862ddcde08ca04c4f7908ef57.jpg</path>
	<source>
		<database>roboflow.ai</database>
	</source>
	<size>
		<width>416</width>
		<height>416</height>
		<depth>3</depth>
	</size>
	<segmented>0</segmented>
	<object>
		<name>face</name>
		<pose>Unspecified</pose>
		<truncated>0</truncated>
		<difficult>0</difficult>
		<occluded>0</occluded>
		<bndbox>
			<xmin>143</xmin>
			<xmax>284</xmax>
			<ymin>22</ymin>
			<ymax>185</ymax>
		</bndbox>
	</object>
</annotation>
