<annotation>
	<folder></folder>
	<filename>img_552_jpg.rf.139a64f18204561067199e71e15a9276.jpg</filename>
	<path>img_552_jpg.rf.139a64f18204561067199e71e15a9276.jpg</path>
	<source>
		<database>roboflow.ai</database>
	</source>
	<size>
		<width>416</width>
		<height>416</height>
		<depth>3</depth>
	</size>
	<segmented>0</segmented>
	<object>
		<name>face</name>
		<pose>Unspecified</pose>
		<truncated>0</truncated>
		<difficult>0</difficult>
		<occluded>0</occluded>
		<bndbox>
			<xmin>111</xmin>
			<xmax>285</xmax>
			<ymin>13</ymin>
			<ymax>167</ymax>
		</bndbox>
	</object>
</annotation>
