<annotation>
	<folder></folder>
	<filename>img_492_jpg.rf.72d88082c998409266827d8a8355e401.jpg</filename>
	<path>img_492_jpg.rf.72d88082c998409266827d8a8355e401.jpg</path>
	<source>
		<database>roboflow.ai</database>
	</source>
	<size>
		<width>416</width>
		<height>416</height>
		<depth>3</depth>
	</size>
	<segmented>0</segmented>
	<object>
		<name>face</name>
		<pose>Unspecified</pose>
		<truncated>0</truncated>
		<difficult>0</difficult>
		<occluded>0</occluded>
		<bndbox>
			<xmin>152</xmin>
			<xmax>215</xmax>
			<ymin>48</ymin>
			<ymax>210</ymax>
		</bndbox>
	</object>
	<object>
		<name>face</name>
		<pose>Unspecified</pose>
		<truncated>0</truncated>
		<difficult>0</difficult>
		<occluded>0</occluded>
		<bndbox>
			<xmin>309</xmin>
			<xmax>373</xmax>
			<ymin>29</ymin>
			<ymax>182</ymax>
		</bndbox>
	</object>
</annotation>
