<annotation>
	<folder></folder>
	<filename>img_241_jpg.rf.72687f5657bb57ea0bf5d80fd545e37c.jpg</filename>
	<path>img_241_jpg.rf.72687f5657bb57ea0bf5d80fd545e37c.jpg</path>
	<source>
		<database>roboflow.ai</database>
	</source>
	<size>
		<width>416</width>
		<height>416</height>
		<depth>3</depth>
	</size>
	<segmented>0</segmented>
	<object>
		<name>face</name>
		<pose>Unspecified</pose>
		<truncated>0</truncated>
		<difficult>0</difficult>
		<occluded>0</occluded>
		<bndbox>
			<xmin>88</xmin>
			<xmax>179</xmax>
			<ymin>25</ymin>
			<ymax>202</ymax>
		</bndbox>
	</object>
</annotation>
