<annotation>
	<folder></folder>
	<filename>img_415_jpg.rf.a2702ee91cb04c245689c6da81f8070c.jpg</filename>
	<path>img_415_jpg.rf.a2702ee91cb04c245689c6da81f8070c.jpg</path>
	<source>
		<database>roboflow.ai</database>
	</source>
	<size>
		<width>416</width>
		<height>416</height>
		<depth>3</depth>
	</size>
	<segmented>0</segmented>
	<object>
		<name>face</name>
		<pose>Unspecified</pose>
		<truncated>0</truncated>
		<difficult>0</difficult>
		<occluded>0</occluded>
		<bndbox>
			<xmin>6</xmin>
			<xmax>107</xmax>
			<ymin>83</ymin>
			<ymax>270</ymax>
		</bndbox>
	</object>
	<object>
		<name>face</name>
		<pose>Unspecified</pose>
		<truncated>0</truncated>
		<difficult>0</difficult>
		<occluded>0</occluded>
		<bndbox>
			<xmin>244</xmin>
			<xmax>374</xmax>
			<ymin>36</ymin>
			<ymax>280</ymax>
		</bndbox>
	</object>
</annotation>
